{"orderid": 1, "code": 2, "table": 3, "snapshot": 4, "flink": 5, "mar": 6, "nov": 7, "test": 8, "type": 9, "error": 10, "use": 11, "sql": 12, "file": 13, "add": 14, "time": 15, "java": 16, "dec": 17, "method": 18, "fail": 19, "jul": 20, "aug": 21, "introduce": 22, "create": 23, "support": 24, "class": 25, "remove": 26, "exception": 27, "connector": 28, "run": 29, "set": 30, "api": 31, "function": 32, "new": 33, "user": 34, "store": 35, "cause": 36, "job": 37, "need": 38, "feb": 39, "currently": 40, "null": 41, "planner": 42, "default": 43, "failure": 44, "catalog": 45, "dependency": 46, "work": 47, "source": 48, "update": 49, "value": 50, "select": 51, "case": 52, "module": 53, "apr": 54, "scala": 55, "jar": 56, "hive": 57, "travis": 58, "instead": 59, "interface": 60, "implement": 61, "format": 62, "string": 63, "partition": 64, "end": 65, "blink": 66, "check": 67, "order": 68, "elapse": 69, "info": 70, "start": 71, "read": 72, "implementation": 73, "fix": 74, "cast": 75, "expression": 76, "base": 77, "slot": 78, "cluster": 79, "allow": 80, "register": 81, "sink": 82, "configuration": 83, "build": 84, "thread": 85, "leader": 86, "example": 87, "throw": 88, "change": 89, "issue": 90, "like": 91, "include": 92, "skip": 93, "result": 94, "follow": 95, "jobmaster": 96, "return": 97, "object": 98, "state": 99, "problem": 100, "log": 101, "system": 102, "way": 103, "legacy": 104, "datum": 105, "old": 106, "checkpoint": 107, "list": 108, "long": 109, "main": 110, "possible": 111, "directory": 112, "path": 113, "rest": 114, "multiple": 115, "stream": 116, "taskexecutor": 117, "query": 118, "try": 119, "contain": 120, "dispatcher": 121, "savepoint": 122, "notice": 123, "require": 124, "find": 125, "noformat": 126, "record": 127, "field": 128, "client": 129, "well": 130, "call": 131, "information": 132, "component": 133, "wait": 134, "column": 135, "schema": 136, "factory": 137, "logic": 138, "improve": 139, "suggest": 140, "access": 141, "mode": 142, "apache": 143, "propose": 144, "message": 145, "simplify": 146, "public": 147, "define": 148, "non": 149, "drop": 150, "deprecate": 151, "stop": 152, "operator": 153, "version": 154, "option": 155, "kafka": 156, "properly": 157, "memory": 158, "bucket": 159, "dist": 160, "int": 161, "array": 162, "stack": 163, "operation": 164, "execute": 165, "reason": 166, "group": 167, "static": 168, "documentation": 169, "extend": 170, "avoid": 171, "internal": 172, "second": 173, "request": 174, "shut": 175, "block": 176, "process": 177, "classloader": 178, "task": 179, "metric": 180, "plugin": 181, "statement": 182, "insert": 183, "parameter": 184, "write": 185, "performance": 186, "compaction": 187, "provide": 188, "restart": 189, "property": 190, "expect": 191, "bundle": 192, "available": 193, "profile": 194, "current": 195, "enable": 196, "directly": 197, "structure": 198, "exist": 199, "expose": 200, "specific": 201, "execution": 202, "python": 203, "row": 204, "similar": 205, "constructor": 206, "configure": 207, "key": 208, "line": 209, "testing": 210, "simple": 211, "happen": 212, "document": 213, "different": 214, "common": 215, "runtime": 216, "compile": 217, "leak": 218, "give": 219, "data": 220, "changelog": 221, "assertionerror": 222, "batch": 223, "leadership": 224, "lose": 225, "look": 226, "final": 227, "yarn": 228, "endpoint": 229, "orc": 230, "make": 231, "structured": 232, "correct": 233, "let": 234, "port": 235, "dynamic": 236, "status": 237, "metadata": 238, "strategy": 239, "clean": 240, "join": 241, "know": 242, "writer": 243, "address": 244, "calcite": 245, "necessary": 246, "service": 247, "reading": 248, "come": 249, "produce": 250, "inference": 251, "close": 252, "taskmanager": 253, "okio": 254, "generate": 255, "logical": 256, "collection": 257, "serializer": 258, "lead": 259, "temporary": 260, "word": 261, "database": 262, "distribution": 263, "web": 264, "describe": 265, "json": 266, "optimize": 267, "break": 268, "ensure": 269, "serialization": 270, "maven": 271, "want": 272, "valid": 273, "report": 274, "convert": 275, "future": 276, "lock": 277, "branch": 278, "datastream": 279, "wrong": 280, "typeinformation": 281, "docker": 282, "output": 283, "merge": 284, "elasticsearch": 285, "disable": 286, "conversion": 287, "split": 288, "miss": 289, "able": 290, "root": 291, "resourcemanager": 292, "complete": 293, "timeout": 294, "window": 295, "upload": 296, "avro": 297, "ddl": 298, "anymore": 299, "easy": 300, "config": 301, "reference": 302, "get": 303, "buffer": 304, "bigint": 305, "count": 306, "copy": 307, "usage": 308, "discuss": 309, "illegalstateexception": 310, "submission": 311, "step": 312, "host": 313, "subtask": 314, "free": 315, "filesystem": 316, "warn": 317, "unnecessary": 318, "refactor": 319, "additional": 320, "serialize": 321, "etc": 322, "creation": 323, "depend": 324, "connection": 325, "interval": 326, "equal": 327, "hashcode": 328, "float": 329, "plan": 330, "actually": 331, "commit": 332, "correctly": 333, "bump": 334, "feature": 335, "binary": 336, "specify": 337, "hadoop": 338, "utility": 339, "integrate": 340, "occur": 341, "aggregate": 342, "open": 343, "view": 344, "command": 345, "daemon": 346, "reuse": 347, "session": 348, "closed": 349, "compatible": 350, "relax": 351, "fully": 352, "name": 353, "executionconfig": 354, "environment": 355, "print": 356, "separate": 357, "size": 358, "recover": 359, "potentially": 360, "regression": 361, "doc": 362, "good": 363, "think": 364, "entry": 365, "additionally": 366, "upgrade": 367, "lot": 368, "custom": 369, "match": 370, "cataloglock": 371, "master": 372, "streaming": 373, "parse": 374, "abstract": 375, "scalarfunction": 376, "listener": 377, "declarativeslotpool": 378, "sure": 379, "fulfil": 380, "offer": 381, "decouple": 382, "cache": 383, "batchtableenvironment": 384, "proper": 385, "migrate": 386, "azure": 387, "late": 388, "allocation": 389, "number": 390, "catch": 391, "release": 392, "resource": 393, "spark": 394, "processing": 395, "timestamp": 396, "jobmanager": 397, "reduce": 398, "jackson": 399, "assemblerclass": 400, "rescale": 401, "handler": 402, "trigger": 403, "finish": 404, "actor": 405, "send": 406, "sort": 407, "filter": 408, "silently": 409, "invalid": 410, "dataset": 411, "assume": 412, "ioexception": 413, "resolution": 414, "rpc": 415, "behavior": 416, "catalogmanager": 417, "currentcnt": 418, "accumulator": 419, "unified": 420, "union": 421, "constraint": 422, "mention": 423, "immutable": 424, "alternative": 425, "generation": 426, "instance": 427, "incorrect": 428, "helpful": 429, "compileexception": 430, "primary": 431, "rename": 432, "library": 433, "idea": 434, "project": 435, "deployment": 436, "page": 437, "explicitly": 438, "accept": 439, "driver": 440, "solve": 441, "artifact": 442, "handle": 443, "uber": 444, "tell": 445, "serializable": 446, "general": 447, "modify": 448, "producer": 449, "github": 450, "following": 451, "submit": 452, "jobgraph": 453, "safe": 454, "literal": 455, "aws": 456, "sdk": 457, "goal": 458, "src": 459, "couple": 460, "replace": 461, "scalar": 462, "actual": 463, "double": 464, "reproduce": 465, "clash": 466, "jdbclookupfunction": 467, "executor": 468, "script": 469, "azp": 470, "byte": 471, "pass": 472, "configurable": 473, "dedicated": 474, "clear": 475, "high": 476, "manifest": 477, "stacktrace": 478, "akka": 479, "asktimeoutexception": 480, "shaded": 481, "kinesis": 482, "setup": 483, "blocking": 484, "streamtableenvironment": 485, "simply": 486, "unit": 487, "optimization": 488, "shuffle": 489, "swallow": 490, "blob": 491, "updaterequest": 492, "action": 493, "continuousfilereaderoperator": 494, "weight": 495, "declare": 496, "watermark": 497, "input": 498, "resume": 499, "spotless": 500, "compute": 501, "immediately": 502, "fencedrpcendpoint": 503, "failover": 504, "retraction": 505, "codegen": 506, "streamoperatorfactory": 507, "filestore": 508, "continuous": 509, "confluent": 510, "backwards": 511, "concept": 512, "enforce": 513, "assign": 514, "variable": 515, "customcommandline": 516, "maintainability": 517, "registration": 518, "place": 519, "dialect": 520, "sec": 521, "important": 522, "control": 523, "claim": 524, "restore": 525, "section": 526, "possibility": 527, "deprecated": 528, "logicaltype": 529, "purpose": 530, "jdbc": 531, "misleading": 532, "pattern": 533, "jdk": 534, "core": 535, "regular": 536, "force": 537, "netty": 538, "part": 539, "package": 540, "shading": 541, "large": 542, "compatibility": 543, "tablesink": 544, "lack": 545, "primitive": 546, "one": 547, "global": 548, "relate": 549, "callable": 550, "void": 551, "easily": 552, "slotpool": 553, "inconsistent": 554, "org": 555, "bug": 556, "determine": 557, "probably": 558, "moment": 559, "problematic": 560, "pende": 561, "cover": 562, "converter": 563, "gain": 564, "election": 565, "tenv": 566, "initialization": 567, "validate": 568, "prevent": 569, "suffix": 570, "benchmark": 571, "term": 572, "unsupportedoperationexception": 573, "attempt": 574, "calculation": 575, "console": 576, "logging": 577, "optional": 578, "consistent": 579, "overhead": 580, "map": 581, "date": 582, "datatype": 583, "bashjavautil": 584, "jvm": 585, "display": 586, "metricqueryservice": 587, "taskmanagers": 588, "duration": 589, "switch": 590, "dsl": 591, "bin": 592, "parallelism": 593, "slice": 594, "developer": 595, "consider": 596, "single": 597, "metricgroup": 598, "asynchronous": 599, "functionality": 600, "rowtype": 601, "cancel": 602, "bash": 603, "resolve": 604, "extract": 605, "basic": 606, "suppress": 607, "license": 608, "compact": 609, "presto": 610, "missing": 611, "shade": 612, "computation": 613, "nullpointerexception": 614, "omit": 615, "varchar": 616, "taskmanagermetricgroup": 617, "instanceid": 618, "setting": 619, "flag": 620, "extra": 621, "help": 622, "hashjoinoperator": 623, "broadcast": 624, "year": 625, "incompatibility": 626, "kind": 627, "tar": 628, "def": 629, "millisecond": 630, "manage": 631, "mytable": 632, "chain": 633, "definition": 634, "difficult": 635, "element": 636, "pipeline": 637, "mean": 638, "unaligned": 639, "solution": 640, "cleanup": 641, "reader": 642, "especially": 643, "recovery": 644, "unexpected": 645, "people": 646, "inputstatus": 647, "condition": 648, "true": 649, "inputformat": 650, "mapper": 651, "adjust": 652, "shortcoming": 653, "respect": 654, "zone": 655, "npe": 656, "suspend": 657, "show": 658, "receiver": 659, "event": 660, "blobcacheservice": 661, "blobserver": 662, "indirectly": 663, "party": 664, "google": 665, "meta": 666, "inf": 667, "functiondefinition": 668, "builtin": 669, "clashing": 670, "externalcatalog": 671, "flinkexception": 672, "confirmation": 673, "jira": 674, "jmxreporterfactorytest": 675, "operatorwrapper": 676, "statementset": 677, "delete": 678, "nullable": 679, "impossible": 680, "optionaldescription": 681, "nested": 682, "instable": 683, "blinkexecutorfactory": 684, "extraction": 685, "identify": 686, "have": 687, "relatively": 688, "typeserializer": 689, "statedescriptor": 690, "attribute": 691, "spillable": 692, "remote": 693, "datagen": 694, "enforced": 695, "cnt": 696, "clifrontend": 697, "testability": 698, "flinkdistribution": 699, "locate": 700, "hook": 701, "back": 702, "flinkresource": 703, "limitation": 704, "overwrite": 705, "limit": 706, "dispatchertest": 707, "retry": 708, "subsume": 709, "broken": 710, "drain": 711, "detail": 712, "difference": 713, "pull": 714, "aim": 715, "jobmasterstopwithsavepointitcase": 716, "illegalstate": 717, "commons": 718, "hbase": 719, "prefix": 720, "stability": 721, "slicingwindowaggoperatorbuilder": 722, "streamingwithstatetestbase": 723, "later": 724, "load": 725, "closurecleaner": 726, "flinkkafkapartitioner": 727, "fat": 728, "packaging": 729, "constant": 730, "migrationversion": 731, "abc": 732, "validationexception": 733, "consume": 734, "maybe": 735, "thing": 736, "caller": 737, "context": 738, "shell": 739, "wonder": 740, "git": 741, "mvn": 742, "target": 743, "val": 744, "connectexception": 745, "refuse": 746, "testingcheckpointidcounter": 747, "builder": 748, "temporal": 749, "orders": 750, "rateshistorywithpk": 751, "outside": 752, "testcompile": 753, "visible": 754, "rowdatatypeinfo": 755, "com": 756, "disappear": 757, "sqltooperationconverter": 758, "unused": 759, "miniclusterconfiguration": 760, "loose": 761, "leadercontender": 762, "compileutil": 763, "stackoverflowerror": 764, "executionenvironment": 765, "env": 766, "streamingfilewriter": 767, "indicate": 768, "engine": 769, "corresponding": 770, "rule": 771, "distribute": 772, "respective": 773, "clusteroverviewhandler": 774, "abstractresthandler": 775, "container": 776, "tablefactory": 777, "validation": 778, "functioncatalog": 779, "unsuccessful": 780, "prior": 781, "dimension": 782, "useful": 783, "lookup": 784, "jdbclookuptablesource": 785, "numbucket": 786, "entirely": 787, "involve": 788, "debug": 789, "confluence": 790, "working": 791, "node": 792, "random": 793, "flinkminicluster": 794, "typesafe": 795, "subsequent": 796, "form": 797, "refactoring": 798, "timestampdiff": 799, "present": 800, "independent": 801, "minimize": 802, "decimal": 803, "bigdecimal": 804, "remain": 805, "completely": 806, "cron": 807, "preserve": 808, "bashjavautils": 809, "differ": 810, "false": 811, "range": 812, "postgres": 813, "bulkformatfactory": 814, "filesource": 815, "bulkformat": 816, "parquet": 817, "hang": 818, "monitor": 819, "piece": 820, "push": 821, "transmit": 822, "extension": 823, "poll": 824, "effect": 825, "entrypoint": 826, "clusterentrypoints": 827, "represent": 828, "listview": 829, "currentjobsoverviewhandler": 830, "overview": 831, "develop": 832, "typefactory": 833, "comment": 834, "availability": 835, "heap": 836, "specializedfunction": 837, "fieldsdatatype": 838, "cancellation": 839, "mail": 840, "language": 841, "text": 842, "tableexception": 843, "dispose": 844, "equivalent": 845, "parser": 846, "mock": 847, "datadoghttpclienttest": 848, "powermock": 849, "detector": 850, "relevant": 851, "minio": 852, "ask": 853, "hivemodule": 854, "apply": 855, "argument": 856, "restserverendpoint": 857, "amazon": 858, "dynamodb": 859, "mergetreewriter": 860, "unstable": 861, "speed": 862, "point": 863, "resolvedschema": 864, "receive": 865, "heartbeat": 866, "udf": 867, "noclassdeffounderror": 868, "resourcemanagerrunner": 869, "unrecognized": 870, "taskmanagershandler": 871, "resourceid": 872, "lifetime": 873, "forkcount": 874, "explicit": 875, "zookeepersubmittedjobgraphstore": 876, "extrafile": 877, "datafilemeta": 878, "override": 879, "granularity": 880, "longhashjoingenerator": 881, "hash": 882, "tool": 883, "generic": 884, "mockito": 885, "manager": 886, "sleep": 887, "executiongraph": 888, "testtimedoutexception": 889, "taskmanagerprocessfailurebatchrecoveryitcase": 890, "program": 891, "share": 892, "aggregatecall": 893, "revisit": 894, "agg": 895, "filesystemtablesink": 896, "gaoyunhaii": 897, "attach": 898, "runtimecontext": 899, "requestindexer": 900, "stage": 901, "akkarpcservicetest": 902, "writing": 903, "usually": 904, "filesystemblobstore": 905, "flush": 906, "disk": 907, "permission": 908, "deny": 909, "connect": 910, "socket": 911, "temporalsort": 912, "clusterentrypoint": 913, "terminate": 914, "supportssourcewatermark": 915, "deeply": 916, "hivedialectqueryitcase": 917, "particular": 918, "scope": 919, "outputtag": 920, "inserializer": 921, "fencing": 922, "previous": 923, "retain": 924, "debeziumavroformatfactory": 925, "supported": 926, "seven": 927, "dev": 928, "online": 929, "category": 930, "item": 931, "precede": 932, "note": 933, "changeflag": 934, "mechanism": 935, "boolean": 936, "incompatible": 937, "mapping": 938, "reactive": 939, "ingest": 940, "threadlocalcache": 941, "content": 942, "migration": 943, "checkstyle": 944, "suppression": 945, "formatting": 946, "recommend": 947, "detach": 948, "leave": 949, "timeoutcallstacktest": 950, "akkarpcactoroversizedresponsemessagetest": 951, "retryingregistration": 952, "hard": 953, "pruning": 954, "wrongly": 955, "translate": 956, "month": 957, "checker": 958, "redundant": 959, "quick": 960, "sourcereader": 961, "comparison": 962, "efficient": 963, "ship": 964, "requirement": 965, "resourcerequirement": 966, "datatypelookup": 967, "consequently": 968, "link": 969, "privacy": 970, "policy": 971, "socketserver": 972, "predicate": 973, "asserializablestre": 974, "experience": 975, "webmonitorendpoint": 976, "perform": 977, "discover": 978, "insufficient": 979, "timezone": 980, "acknowledge": 981, "finalize": 982, "akkarpcsystemloader": 983, "standalonejobclusterentrypoint": 984, "blockstatementgrouper": 985, "oom": 986, "abstraction": 987, "management": 988, "queryable": 989, "nonbufferoverwindowoperator": 990, "overwindowframe": 991, "broadcastemit": 992, "iceberg": 993, "blobservice": 994, "parquetfsstreamingsinkitcase": 995, "listing": 996, "intellij": 997, "arrive": 998, "tinyint": 999, "smallint": 1000, "generalize": 1001, "util": 1002, "continue": 1003, "getkind": 1004, "gettypeinference": 1005, "resultpartitiondeploymentdescriptor": 1006, "cookie": 1007, "gzip": 1008, "encapsulate": 1009, "initially": 1010, "readablecatalog": 1011, "externalcatalogschema": 1012, "catalogtable": 1013, "externalcatalogtable": 1014, "assembly": 1015, "skeletal": 1016, "leftover": 1017, "allocate": 1018, "kubernetes": 1019, "standalone": 1020, "mutable": 1021, "jobmanagerrunner": 1022, "typeinferenceoperandchecker": 1023, "pure": 1024, "invocationtargetexception": 1025, "sub": 1026, "virtual": 1027, "pythonplanbindertest": 1028, "bot": 1029, "unassign": 1030, "ticket": 1031, "vendor": 1032, "repository": 1033, "take": 1034, "streamstatementset": 1035, "fileuploadhandler": 1036, "registry": 1037, "turn": 1038, "topic": 1039, "alter": 1040, "newt": 1041, "formatted": 1042, "jsonize": 1043, "inline": 1044, "anonymous": 1045, "identifi": 1046, "qualified": 1047, "batchexecutionkeyedstatebackend": 1048, "freshly": 1049, "construct": 1050, "getorcreatekeyedstate": 1051, "namespaceserializer": 1052, "namespace": 1053, "checknotnull": 1054, "keyserializer": 1055, "obtain": 1056, "self": 1057, "transitively": 1058, "overflow": 1059, "unknown": 1060, "dfs": 1061, "greatly": 1062, "affect": 1063, "writebuffer": 1064, "responsible": 1065, "bit": 1066, "inflexible": 1067, "responsibility": 1068, "demote": 1069, "wrapper": 1070, "programmatic": 1071, "mutate": 1072, "interact": 1073, "syntax": 1074, "partitioned": 1075, "fatally": 1076, "naming": 1077, "accident": 1078, "hiding": 1079, "neat": 1080, "constrainst": 1081, "verify": 1082, "phase": 1083, "better": 1084, "distinction": 1085, "stable": 1086, "explain": 1087, "semantic": 1088, "flip": 1089, "notes": 1090, "tab": 1091, "cli": 1092, "highlight": 1093, "degreeswithexceptionitcase": 1094, "crash": 1095, "big": 1096, "backpressure": 1097, "period": 1098, "perplexity": 1099, "ops": 1100, "enablesysoutlogge": 1101, "isfailtaskoncheckpointerror": 1102, "argue": 1103, "guarantee": 1104, "logicaltypes": 1105, "subsequence": 1106, "metaspace": 1107, "folder": 1108, "parent": 1109, "loaded": 1110, "recursively": 1111, "dig": 1112, "transient": 1113, "reflective": 1114, "reflection": 1115, "strings": 1116, "bigdecimals": 1117, "rework": 1118, "classifier": 1119, "mantras": 1120, "importance": 1121, "mantra": 1122, "downstream": 1123, "categorically": 1124, "manually": 1125, "cut": 1126, "proposal": 1127, "original": 1128, "warning": 1129, "folding": 1130, "physical": 1131, "retract": 1132, "upsert": 1133, "interpolation": 1134, "inconvenient": 1135, "valuevar": 1136, "genericarraydata": 1137, "hivecatalog": 1138, "transaction": 1139, "closeable": 1140, "mark": 1141, "dynamictablefactory": 1142, "requirecataloglock": 1143, "lockfactory": 1144, "limited": 1145, "instruction": 1146, "clone": 1147, "finally": 1148, "jobsubmissionexception": 1149, "completionexception": 1150, "npes": 1151, "surprising": 1152, "pointer": 1153, "cryptic": 1154, "char": 1155, "timestampstring": 1156, "unique": 1157, "xmlresponsessaxparser": 1158, "compiler": 1159, "compilation": 1160, "repos": 1161, "tostre": 1162, "origin": 1163, "tostring": 1164, "brake": 1165, "paramter": 1166, "yield": 1167, "myfunc": 1168, "lon": 1169, "lat": 1170, "reducer": 1171, "tableschema": 1172, "mergetablelikeutil": 1173, "instantiate": 1174, "registernewslotlistener": 1175, "sortbuffermemtable": 1176, "seize": 1177, "preempt": 1178, "preemptable": 1179, "integrity": 1180, "reachable": 1181, "classloaders": 1182, "strong": 1183, "stackoverflowerrorexception": 1184, "feedback": 1185, "forget": 1186, "listen": 1187, "resolvedcatalogtable": 1188, "bucketcomputer": 1189, "supportswrite": 1190, "dock": 1191, "streamtablesourcefactory": 1192, "dependencie": 1193, "sortaggregate": 1194, "hashaggregate": 1195, "batchexecsortaggregate": 1196, "batchexechashaggregate": 1197, "aggitcase": 1198, "rid": 1199, "legacyresthandler": 1200, "improvement": 1201, "apart": 1202, "environmentsettings": 1203, "yaml": 1204, "background": 1205, "past": 1206, "hiveoption": 1207, "natural": 1208, "jdbccatalog": 1209, "postgrescatalog": 1210, "postgre": 1211, "trace": 1212, "sqlexecutionexception": 1213, "invalidate": 1214, "parenthesis": 1215, "abstractjdbccatalog": 1216, "allocationid": 1217, "bucketselector": 1218, "negative": 1219, "testexecutorresource": 1220, "manual": 1221, "japicmp": 1222, "clutter": 1223, "considerably": 1224, "nowadays": 1225, "unify": 1226, "zziqcw": 1227, "persistent": 1228, "volume": 1229, "newly": 1230, "usable": 1231, "lookupjoinitcase": 1232, "userdefinedfunctionhelper": 1233, "javascala": 1234, "interplay": 1235, "detect": 1236, "difficulty": 1237, "mixup": 1238, "clusterdescriptors": 1239, "development": 1240, "expressionconverter": 1241, "rexnodeconverter": 1242, "classification": 1243, "maintain": 1244, "stre": 1245, "timepointunit": 1246, "files": 1247, "poor": 1248, "filestoretablefactory": 1249, "conducive": 1250, "baserow": 1251, "basemap": 1252, "basearray": 1253, "basestring": 1254, "automatically": 1255, "basegeneric": 1256, "genericreldatatype": 1257, "boxed": 1258, "correspond": 1259, "launchcoordinatortest": 1260, "calculate": 1261, "ideally": 1262, "nice": 1263, "rewrite": 1264, "align": 1265, "multiinputmapsink": 1266, "multiinputoneidlemapsink": 1267, "readfilesplit": 1268, "parquetfilesystemformatfactory": 1269, "blocked": 1270, "sslsocketoutputrecord": 1271, "unilateralsortmerger": 1272, "preparation": 1273, "fold": 1274, "composable": 1275, "manner": 1276, "webui": 1277, "adverse": 1278, "serve": 1279, "versioning": 1280, "scheme": 1281, "converting": 1282, "essential": 1283, "idiomatic": 1284, "pack": 1285, "small": 1286, "algorithm": 1287, "packing": 1288, "fragment": 1289, "tree": 1290, "suppose": 1291, "intersection": 1292, "fast": 1293, "fine": 1294, "binpack": 1295, "tablestorecatalog": 1296, "unsupported": 1297, "capability": 1298, "tablestore": 1299, "singleton": 1300, "singlevalueaggfunction": 1301, "accord": 1302, "throwexception": 1303, "expr": 1304, "zookeeperhaservice": 1305, "kuberneteshaservice": 1306, "jarlisthandler": 1307, "jarfile": 1308, "laben": 1309, "reliance": 1310, "usual": 1311, "pom": 1312, "automate": 1313, "obviously": 1314, "uberjar": 1315, "equals": 1316, "abstractasynchronousoperationhandler": 1317, "spuriously": 1318, "getfielddatatype": 1319, "location": 1320, "iterate": 1321, "datatypes": 1322, "fieldname": 1323, "fieldtypes": 1324, "jobterminationhandler": 1325, "compiledplan": 1326, "deserialize": 1327, "bridgingsqlfunction": 1328, "missingtypestrategy": 1329, "unable": 1330, "formatter": 1331, "actionscript": 1332, "ada": 1333, "applescript": 1334, "cpp": 1335, "css": 1336, "erlang": 1337, "groovy": 1338, "haskell": 1339, "html": 1340, "javascript": 1341, "lua": 1342, "nyan": 1343, "objc": 1344, "perl": 1345, "php": 1346, "rainbow": 1347, "ruby": 1348, "swift": 1349, "visualbasic": 1350, "xml": 1351, "yamlcause": 1352, "modulemanager": 1353, "sinkwriter": 1354, "globalcommitter": 1355, "contract": 1356, "nasty": 1357, "workaround": 1358, "employ": 1359, "transport": 1360, "enhancement": 1361, "tcp": 1362, "confusion": 1363, "reporting": 1364, "pre": 1365, "jobsubmission": 1366, "wordcount": 1367, "unavailable": 1368, "perspective": 1369, "localfencedmessage": 1370, "typical": 1371, "recipient": 1372, "reply": 1373, "hivemoduletest": 1374, "formal": 1375, "length": 1376, "licensed": 1377, "appear": 1378, "kms": 1379, "adapter": 1380, "cep": 1381, "machine": 1382, "async": 1383, "impact": 1384, "logstore": 1385, "latency": 1386, "press": 1387, "num": 1388, "scm": 1389, "developerconnection": 1390, "schemaresolver": 1391, "clusterpartitionreport": 1392, "inner": 1393, "reporter": 1394, "facebook": 1395, "hadoopfilestatus": 1396, "minicluster": 1397, "fashion": 1398, "imperative": 1399, "environmentsetting": 1400, "udaf": 1401, "argtypes": 1402, "hiveaggsqlfunction": 1403, "istableaggregate": 1404, "mydatagen": 1405, "imo": 1406, "bind": 1407, "effectively": 1408, "implication": 1409, "retrieve": 1410, "far": 1411, "toggle": 1412, "story": 1413, "filename": 1414, "index": 1415, "taskmanagerrunner": 1416, "commandlineparser": 1417, "memorysize": 1418, "occasion": 1419, "right": 1420, "readable": 1421, "longhybridhashtable": 1422, "longhashjoinoperator": 1423, "totally": 1424, "outdated": 1425, "refer": 1426, "generics": 1427, "investigate": 1428, "flinksecuritymanager": 1429, "security": 1430, "illegalconfigurationexception": 1431, "locally": 1432, "testjobstatuslistenernotifiedofjobstatuschange": 1433, "loop": 1434, "termination": 1435, "jobstatuschangelistener": 1436, "notify": 1437, "assertion": 1438, "jobstatus": 1439, "restartingtime": 1440, "trivla": 1441, "defaultscheduler": 1442, "adaptivescheduler": 1443, "expressionbridge": 1444, "queryoperations": 1445, "bridge": 1446, "queryoperation": 1447, "resolvedexpression": 1448, "prepare": 1449, "checkpointstatstracker": 1450, "coordinator": 1451, "tracker": 1452, "bother": 1453, "misinterpret": 1454, "varargs": 1455, "vararg": 1456, "signature": 1457, "harden": 1458, "directorie": 1459, "otherwisely": 1460, "stale": 1461, "nosuchmethoderror": 1462, "bulk": 1463, "bulkprocessor": 1464, "elasticsearchsinkfunction": 1465, "import": 1466, "myindex": 1467, "bulkprocessorindexer": 1468, "continuousfilereaderoperatorbenchmark": 1469, "reset": 1470, "warmup": 1471, "iteration": 1472, "anticipate": 1473, "world": 1474, "rowdata": 1475, "orcrowdatainputformat": 1476, "rowdatavectorizer": 1477, "orcfilesystemformatfactory": 1478, "streamnode": 1479, "managed": 1480, "transformation": 1481, "managedmemoryusecase": 1482, "factor": 1483, "kibi": 1484, "persist": 1485, "fsynced": 1486, "post": 1487, "dial": 1488, "unix": 1489, "chainingstrategy": 1490, "similarly": 1491, "deserializationschema": 1492, "pubsub": 1493, "rabbitmq": 1494, "fork": 1495, "pool": 1496, "shutdownandterminate": 1497, "metastore": 1498, "ability": 1499, "generated": 1500, "analyze": 1501, "applysourcewatermark": 1502, "operatorchain": 1503, "straightforward": 1504, "minimal": 1505, "production": 1506, "disabled": 1507, "copyingchainingoutput": 1508, "fence": 1509, "automatic": 1510, "fencerpcendpoint": 1511, "resourcemanagerid": 1512, "uuid": 1513, "token": 1514, "understand": 1515, "slow": 1516, "expire": 1517, "filenotfoundexception": 1518, "excepion": 1519, "checking": 1520, "nightly": 1521, "types": 1522, "sentence": 1523, "suggestion": 1524, "attached": 1525, "screenshot": 1526, "trivial": 1527, "thx": 1528, "travel": 1529, "architecture": 1530, "adopt": 1531, "rowkind": 1532, "sockettimeout": 1533, "fileuploadhandlert": 1534, "sockettimeoutexception": 1535, "socketexception": 1536, "taskiometricgroupt": 1537, "encounter": 1538, "immediate": 1539, "intermediate": 1540, "vary": 1541, "degree": 1542, "gate": 1543, "round": 1544, "robin": 1545, "channel": 1546, "accordingly": 1547, "topology": 1548, "artifactset": 1549, "ideal": 1550, "exclude": 1551, "mapview": 1552, "treat": 1553, "lib": 1554, "strip": 1555, "having": 1556, "land": 1557, "opportunity": 1558, "narrow": 1559, "bunch": 1560, "friendly": 1561, "application": 1562, "approach": 1563, "hdfs": 1564, "reconnect": 1565, "gracefully": 1566, "orphan": 1567, "underlie": 1568, "risk": 1569, "akkarpcservicet": 1570, "scenario": 1571, "local": 1572, "sticky": 1573, "scheduling": 1574, "rocksdbkeyedstatebackendbuilder": 1575, "backendrestorerprocedure": 1576, "backend": 1577, "backendbuildingexception": 1578, "faille": 1579, "temp": 1580, "standalonesession": 1581, "logicalwindowaggregate": 1582, "aggregation": 1583, "day": 1584, "powerful": 1585, "dynamictablesource": 1586, "derive": 1587, "response": 1588, "licensechecker": 1589, "familiar": 1590, "bombard": 1591, "guidance": 1592, "critical": 1593, "enum": 1594, "internally": 1595, "clause": 1596, "partially": 1597, "absolute": 1598, "raw": 1599, "circumstance": 1600, "myudf": 1601, "integer": 1602, "getmetricgroup": 1603, "optimisation": 1604, "choice": 1605, "instruct": 1606, "fileformat": 1607, "compactcoordinator": 1608, "compactoperator": 1609, "inputformatsourcefunction": 1610, "testtimedout": 1611, "increase": 1612, "sense": 1613, "building": 1614, "image": 1615, "existence": 1616, "deserialization": 1617, "noticefilechecker": 1618, "barely": 1619, "said": 1620, "jsonnodedeserializationschema": 1621, "rawvaluedata": 1622, "accessing": 1623, "deal": 1624, "actions": 1625, "infra": 1626, "recently": 1627, "credential": 1628, "rsync": 1629, "buildbot": 1630, "maintenance": 1631, "atomicreferenceupdater": 1632, "credentail": 1633, "startup": 1634, "sensitive": 1635, "hide": 1636, "globalconfiguration": 1637, "interaction": 1638, "zoneid": 1639, "theoretical": 1640, "feel": 1641, "confuse": 1642, "currenlty": 1643, "synchronously": 1644, "pendingcheckpoint": 1645, "checkpointexception": 1646, "fallback": 1647, "ide": 1648, "loading": 1649, "certain": 1650, "workflow": 1651, "rebuild": 1652, "alleviate": 1653, "specifically": 1654, "avg": 1655, "min": 1656, "max": 1657, "sum": 1658, "stddevpop": 1659, "stddevsamp": 1660, "varpop": 1661, "varsamp": 1662, "gets": 1663, "completion": 1664, "quickly": 1665, "jm": 1666, "yes": 1667, "coordination": 1668, "safety": 1669, "sender": 1670, "testable": 1671, "wrap": 1672, "received": 1673, "paradigm": 1674, "layout": 1675, "kvstateserver": 1676, "kvstateproxyclient": 1677, "discussion": 1678, "supportsreadingmetadata": 1679, "supportswritingmetadata": 1680, "rank": 1681, "unbounded": 1682, "bufferdataoverwindowoperator": 1683, "duplicate": 1684, "overwindowoperator": 1685, "frame": 1686, "observe": 1687, "symptom": 1688, "delay": 1689, "checkpointing": 1690, "localbufferpool": 1691, "stracktracegenerator": 1692, "see": 1693, "network": 1694, "bypass": 1695, "question": 1696, "idle": 1697, "optimise": 1698, "broadcasting": 1699, "cb": 1700, "discard": 1701, "partial": 1702, "emphasize": 1703, "tempting": 1704, "deliver": 1705, "setter": 1706, "jobmanagerconnection": 1707, "wasteful": 1708, "establish": 1709, "propagate": 1710, "reusable": 1711, "tableenvironment": 1712, "tableenvironments": 1713, "purely": 1714, "setoperationfactory": 1715, "parquetfilecompactionitcase": 1716, "analysis": 1717, "aggregatequeryoperation": 1718, "representation": 1719, "values": 1720, "mismatch": 1721, "downgrade": 1722, "var": 1723, "emit": 1724, "likely": 1725, "spam": 1726, "catalogview": 1727, "tricky": 1728, "sqlparser": 1729, "numberformatexception": 1730, "character": 1731, "behaviour": 1732, "arounds": 1733, "sharing": 1734, "safeguard": 1735, "mistake": 1736, "concern": 1737, "restclusterclient": 1738, "move": 1739, "variant": 1740, "lang": 1741, "distinguish": 1742, "udfs": 1743, "rough": 1744, "design": 1745, "separation": 1746, "planning": 1747, "userdefinedfunctiondefinition": 1748, "createimplementation": 1749, "userdefinedfunction": 1750, "builtinfunctiondefinition": 1751, "getname": 1752, "aggregatefunction": 1753, "tablefunction": 1754, "total": 1755, "incomplete": 1756, "initiate": 1757, "conversely": 1758, "accessible": 1759, "candidate": 1760, "partitiondescriptor": 1761, "datasetid": 1762, "castfunctionitcase": 1763, "beginning": 1764, "kerberized": 1765, "download": 1766, "mkdir": 1767, "curl": 1768, "oraclelicense": 1769, "securebackup": 1770, "stdin": 1771, "child": 1772, "hold": 1773, "interrelation": 1774, "cat": 1775, "mimic": 1776, "nesting": 1777, "databasecalciteschema": 1778, "unlikely": 1779, "encode": 1780, "mind": 1781, "initial": 1782, "unalignedcheckpointitcase": 1783, "operatorevent": 1784, "operatorcoordinator": 1785, "consistency": 1786, "nomoresplitevent": 1787, "targettask": 1788, "catalogbasetable": 1789, "declarativeslotmanager": 1790, "account": 1791, "slotreport": 1792, "pending": 1793, "reassign": 1794, "premature": 1795, "configuratiom": 1796, "major": 1797, "debezium": 1798, "complicated": 1799, "entail": 1800, "calciteconfig": 1801, "temporarily": 1802, "tightly": 1803, "defaultleaderretrievalservice": 1804, "retrieval": 1805, "regain": 1806, "casting": 1807, "resolvecallbyargumentsrule": 1808, "track": 1809, "instantiation": 1810, "scanruntimeprovider": 1811, "rely": 1812, "heavily": 1813, "jobexception": 1814, "sortcodegenerator": 1815, "normalizedkey": 1816, "arraytype": 1817, "struct": 1818, "great": 1819, "volatile": 1820, "rare": 1821, "skew": 1822, "regularly": 1823, "porting": 1824, "savepointmigrationtestbase": 1825, "shutdown": 1826, "entire": 1827, "proxy": 1828, "real": 1829, "invoke": 1830, "introduction": 1831, "cost": 1832, "half": 1833, "hour": 1834, "appender": 1835, "logger": 1836, "initialize": 1837, "jstack": 1838, "savepointitcase": 1839, "teststopwithsavepointwithdrainglobalfailoverifsavepointaborte": 1840, "failed": 1841, "bytescolumnvector": 1842, "init": 1843, "revert": 1844, "exactly": 1845, "itcase": 1846, "itcases": 1847, "scan": 1848, "attache": 1849, "attachasdatastream": 1850, "streamexecutionenvironment": 1851, "cursory": 1852, "glance": 1853, "deletion": 1854, "dose": 1855, "incorrectly": 1856}